bargets/__init__.py
bargets/battery.py
bargets/configparser.py
bargets/cpu.py
bargets-0.1.0rc2.dist-info/LICENSE.txt
bargets-0.1.0rc2.dist-info/METADATA
bargets-0.1.0rc2.dist-info/WHEEL
bargets-0.1.0rc2.dist-info/entry_points.txt
bargets-0.1.0rc2.dist-info/top_level.txt
bargets-0.1.0rc2.dist-info/RECORD
