Metadata-Version: 2.1
Name: bargets
Version: 0.1.0rc2
Summary: Tiny arsenal of widgets for statusbars
Author: Niklas Larsson
License: UNKNOWN
Project-URL: Bug Reports, https://github.com/nikkelarsson/bargets/issues
Project-URL: Source, https://github.com/nikkelarsson/bargets
Keywords: widgets utilities statusbars
Platform: UNKNOWN
Classifier: Development Status :: 3 - Alpha
Classifier: Intended Audience :: End Users/Desktop
Classifier: License :: OSI Approved :: MIT License
Classifier: Programming Language :: Python :: 3
Requires-Python: >=3.10
License-File: LICENSE.txt
Requires-Dist: ruamel.yaml
